README.rst
setup.py
src/django_redis_counter.egg-info/PKG-INFO
src/django_redis_counter.egg-info/SOURCES.txt
src/django_redis_counter.egg-info/dependency_links.txt
src/django_redis_counter.egg-info/not-zip-safe
src/django_redis_counter.egg-info/requires.txt
src/django_redis_counter.egg-info/top_level.txt
src/drc/__init__.py
src/drc/admin.py
src/drc/apps.py
src/drc/models.py
src/drc/settings.py
src/drc/storage.py
src/drc/tests.py
src/drc/views.py
src/drc/management/__init__.py
src/drc/management/commands/__init__.py
src/drc/management/commands/drc-dump.py
src/drc/migrations/__init__.py
src/drctest/migrations/0001_initial.py
src/drctest/migrations/__init__.py