Metadata-Version: 1.1
Name: django-redis-counter
Version: 0.1.0
Summary: Django application that keeps content visit count in redis first, then dump to database via extra job.
Home-page: https://github.com/appstore-zencore/django-redis-counter
Author: zencore
Author-email: dobetter@zencore.cn
License: MIT
Keywords: django-redis-counter
Platform: UNKNOWN
Classifier: Development Status :: 5 - Production/Stable
Classifier: Intended Audience :: Developers
Classifier: Topic :: Software Development :: Libraries :: Python Modules
Classifier: License :: OSI Approved :: MIT License
Classifier: Programming Language :: Python :: 3
Classifier: Programming Language :: Python :: 3 :: Only
Requires: django
Requires: django_click
Requires: redis
